get_metadata/__init__.py
get_metadata-0.0.5.dist-info/LICENSE
get_metadata-0.0.5.dist-info/METADATA
get_metadata-0.0.5.dist-info/WHEEL
get_metadata-0.0.5.dist-info/top_level.txt
get_metadata-0.0.5.dist-info/RECORD
