Metadata-Version: 2.1
Name: get-metadata
Version: 0.0.5
Summary: Get metadata string. Works on GAE(Google App Engine), GCF(Google Cloud Functions), and the others.
Home-page: https://github.com/hisashimurai/get_metadata
Author: Hisashi Murai
Author-email: xyksp956@yahoo.co.jp
License: MIT
Keywords: GAE GCF GCP metadata
Platform: UNKNOWN
Classifier: Development Status :: 5 - Production/Stable
Classifier: Programming Language :: Python :: 3
Classifier: Programming Language :: Python :: 3.7
Classifier: Programming Language :: Python :: 3.8
Classifier: Programming Language :: Python :: 3.9
Classifier: License :: OSI Approved :: MIT License
Requires-Python: >=3.7
